README.rst
includer.py
setup.py
includer.egg-info/PKG-INFO
includer.egg-info/SOURCES.txt
includer.egg-info/dependency_links.txt
includer.egg-info/requires.txt
includer.egg-info/top_level.txt