Metadata-Version: 1.1
Name: includer
Version: 1.0.1
Summary: Include and run callables
Home-page: https://github.com/zzzsochi/includer
Author: Alexander Zelenyak
Author-email: zzz.sochi@gmail.com
License: BSD
Keywords: include,configure,pyramid
Platform: UNKNOWN
Classifier: License :: OSI Approved :: BSD License
Classifier: Operating System :: POSIX
Classifier: Programming Language :: Python :: 3
Classifier: Development Status :: 5 - Production/Stable
